langchain_couchbase/__init__.py
langchain_couchbase/cache.py
langchain_couchbase/chat_message_histories.py
langchain_couchbase/py.typed
langchain_couchbase/vectorstores.py
gigachain_couchbase-0.1.1.dist-info/LICENSE
gigachain_couchbase-0.1.1.dist-info/METADATA
gigachain_couchbase-0.1.1.dist-info/WHEEL
gigachain_couchbase-0.1.1.dist-info/RECORD
